pyramid_tiny_utility
