Metadata-Version: 1.0
Name: pyramid-tiny-utility
Version: 0.0.2
Summary: the training wheel for developing with pyramid
Home-page: UNKNOWN
Author: UNKNOWN
Author-email: UNKNOWN
License: UNKNOWN
Platform: UNKNOWN
